properpath/.DS_Store
properpath/__init__.py
properpath/platformdirs_.py
properpath/platformdirs_.pyi
properpath/properpath.py
properpath/py.typed
properpath/validators/__init__.py
properpath/validators/base.py
properpath/validators/validators.py
properpath-0.2.11.dist-info/WHEEL
properpath-0.2.11.dist-info/METADATA
properpath-0.2.11.dist-info/RECORD
