Metadata-Version: 2.4
Name: properpath
Version: 0.2.11
Summary: A pathlib.Path drop-in replacement with extra features. 
Keywords: path
Author: Alexander Haller, Mahadi Xion
Author-email: Alexander Haller, Mahadi Xion <elabftw@uni-heidelberg.de>
License-Expression: MIT
Classifier: Development Status :: 5 - Production/Stable
Classifier: Intended Audience :: Developers
Classifier: Intended Audience :: System Administrators
Classifier: Natural Language :: English
Classifier: Operating System :: OS Independent
Classifier: Topic :: Software Development :: Libraries :: Python Modules
Classifier: Topic :: System :: Systems Administration
Classifier: Topic :: Utilities
Requires-Dist: platformdirs>=4.5.1,<4.6.0
Requires-Dist: pydantic>=2.11.0,<2.13.0 ; extra == 'pydantic'
Requires-Dist: rich>=14.0,<14.3.0 ; extra == 'rich'
Maintainer: Mahadi Xion
Maintainer-email: Mahadi Xion <mahadi.xion@urz.uni-heidelberg.de>
Requires-Python: >=3.12
Project-URL: Changelog, https://github.com/uhd-urz/properpath/blob/main/CHANGELOG.md
Project-URL: Homepage, https://uhd-urz.github.io/properpath/
Project-URL: Issues, https://github.com/uhd-urz/properpath/issues
Project-URL: Repository, https://github.com/uhd-urz/properpath
Provides-Extra: pydantic
Provides-Extra: rich
